debian/changelog
debian/compat
debian/control
debian/copyright
debian/debhelper-build-stamp
debian/files
debian/py3dist-overrides
debian/rules
tt_burnin/__init__.py
tt_burnin/chip.py
tt_burnin/load_ttx.py
tt_burnin/main.py
tt_burnin/utils.py
tt_burnin/ttx/bhpv.ttx
tt_burnin/ttx/whpv.ttx
tt_burnin-0.3.0.dist-info/licenses/LICENSE
tt_burnin-0.3.0.dist-info/licenses/LICENSE_understanding.txt
tt_burnin-0.3.0.dist-info/METADATA
tt_burnin-0.3.0.dist-info/WHEEL
tt_burnin-0.3.0.dist-info/entry_points.txt
tt_burnin-0.3.0.dist-info/top_level.txt
tt_burnin-0.3.0.dist-info/RECORD
