Metadata-Version: 2.4
Name: tt-burnin
Version: 0.3.0
Summary: Run high power workload on all connected chips
Author-email: Daniel Rosen <drosen@tenstorrent.com>
Maintainer-email: Daniel Rosen <drosen@tenstorrent.com>
License: 
Project-URL: Homepage, http://tenstorrent.com
Project-URL: Bug Reports, https://github.com/tenstorrent/tt-burnin/issues
Project-URL: Source, https://github.com/tenstorrent/tt-burnin
Classifier: Development Status :: 4 - Beta
Classifier: Environment :: Console :: Curses
Classifier: License :: OSI Approved :: Apache Software License
Classifier: Programming Language :: Python :: 3
Classifier: Programming Language :: Python :: 3.7
Classifier: Programming Language :: Python :: 3.8
Classifier: Programming Language :: Python :: 3.9
Classifier: Programming Language :: Python :: 3.10
Classifier: Programming Language :: Python :: 3.11
Classifier: Programming Language :: Python :: 3 :: Only
Requires-Python: >=3.10
License-File: LICENSE
License-File: LICENSE_understanding.txt
Requires-Dist: tt_tools_common~=1.5
Requires-Dist: pyluwen~=0.8.0
Requires-Dist: tomli==2.0.1; python_version < "3.11"
Requires-Dist: jsons==1.6.3
Requires-Dist: importlib-metadata==4.11.3; python_version < "3.8"
Provides-Extra: dev
Requires-Dist: black==24.10.0; python_version >= "3.9" and extra == "dev"
Requires-Dist: black==24.8.0; python_version == "3.8" and extra == "dev"
Requires-Dist: black==23.3.0; python_version == "3.7" and extra == "dev"
Dynamic: license-file
Dynamic: requires-python
